synthetic_languages/__init__.py
synthetic_languages/main.py
synthetic_languages-0.0.1.dist-info/METADATA
synthetic_languages-0.0.1.dist-info/WHEEL
synthetic_languages-0.0.1.dist-info/licenses/LICENSE
synthetic_languages-0.0.1.dist-info/RECORD
