Metadata-Version: 2.3
Name: synthetic_languages
Version: 0.0.1
Summary: A package to let you create synthetic languages for the purposes of performing language model interpretability.
Project-URL: Homepage, https://github.com/4gatepylon/synthetic_languages
Project-URL: Issues, https://github.com/4gatepylon/synthetic_languages/issues
Author-email: Adriano Hernandez <adrianoh@mit.edu>
License-File: LICENSE
Classifier: License :: OSI Approved :: MIT License
Classifier: Operating System :: OS Independent
Classifier: Programming Language :: Python :: 3
Requires-Python: >=3.8
Requires-Dist: numpy
Requires-Dist: torch
